RSSMOSPipeline/RSSMOSTools.py
RSSMOSPipeline/__init__.py
RSSMOSPipeline/_version.py
RSSMOSPipeline/data/modelArcSpectra/PG0900_Ar_2x2.txt
RSSMOSPipeline/data/modelArcSpectra/PG0900_Ar_2x2_1.txt
RSSMOSPipeline/data/modelArcSpectra/PG0900_Ne_1x2.txt
RSSMOSPipeline/data/modelArcSpectra/PG0900_Ne_2x2.txt
RSSMOSPipeline/data/modelArcSpectra/PG0900_Ne_2x2_1.txt
RSSMOSPipeline/data/modelArcSpectra/PG0900_Th Ar_2x2.txt
RSSMOSPipeline/data/modelArcSpectra/PG0900_Xe_1x2.txt
RSSMOSPipeline/data/modelArcSpectra/PG0900_Xe_2x2.txt
RSSMOSPipeline/data/modelArcSpectra/PG0900_Xe_2x2_1.txt
RSSMOSPipeline/data/modelArcSpectra/PG1300_Ar_1x2.txt
RSSMOSPipeline/data/modelArcSpectra/PG1300_Ar_2x2.txt
RSSMOSPipeline/data/modelArcSpectra/PG1300_Ar_2x2_1.txt
RSSMOSPipeline/data/modelArcSpectra/PG1300_Cu Ar_2x2.txt
RSSMOSPipeline/data/modelArcSpectra/PG1300_Ne_1x2.txt
RSSMOSPipeline/data/modelArcSpectra/PG1300_Xe_1x2.txt
RSSMOSPipeline/data/modelArcSpectra/PG1800_Ne_2x2.txt
RSSMOSPipeline/data/modelArcSpectra/README
RSSMOSPipeline/data/modelArcSpectra/RefModel_PG0900_Ar_2x2.pickle
RSSMOSPipeline/data/modelArcSpectra/RefModel_PG0900_Ar_2x2_1.pickle
RSSMOSPipeline/data/modelArcSpectra/RefModel_PG0900_Ne_1x2.pickle
RSSMOSPipeline/data/modelArcSpectra/RefModel_PG0900_Ne_2x2.pickle
RSSMOSPipeline/data/modelArcSpectra/RefModel_PG0900_Ne_2x2_1.pickle
RSSMOSPipeline/data/modelArcSpectra/RefModel_PG0900_Th Ar_2x2.pickle
RSSMOSPipeline/data/modelArcSpectra/RefModel_PG0900_Xe_1x2.pickle
RSSMOSPipeline/data/modelArcSpectra/RefModel_PG0900_Xe_2x2.pickle
RSSMOSPipeline/data/modelArcSpectra/RefModel_PG0900_Xe_2x2_1.pickle
RSSMOSPipeline/data/modelArcSpectra/RefModel_PG1300_Ar_1x2.pickle
RSSMOSPipeline/data/modelArcSpectra/RefModel_PG1300_Ar_2x2.pickle
RSSMOSPipeline/data/modelArcSpectra/RefModel_PG1300_Ar_2x2_1.pickle
RSSMOSPipeline/data/modelArcSpectra/RefModel_PG1300_Cu Ar_2x2.pickle
RSSMOSPipeline/data/modelArcSpectra/RefModel_PG1300_Ne_1x2.pickle
rssmospipeline-0.7.0.dist-info/LICENSE
rssmospipeline-0.7.0.dist-info/METADATA
rssmospipeline-0.7.0.dist-info/WHEEL
rssmospipeline-0.7.0.dist-info/top_level.txt
rssmospipeline-0.7.0.dist-info/RECORD
