Metadata-Version: 2.2
Name: RSSMOSPipeline
Version: 0.7.0
Summary: Pipeline for reducing both longslit and multi-object spectroscopic data from the Robert Stobie Spectrograph on the Southern African Large Telescope
Home-page: https://github.com/mattyowl/RSSMOSPipeline
Author: Matt Hilton + RSSMOSPipeline Contributors
Author-email: matt.hilton@wits.ac.za
License: GPL v3
Keywords: astrophysics,astronomy,spectroscopy
Classifier: Programming Language :: Python :: 3
Classifier: Environment :: Console
Classifier: Intended Audience :: Science/Research
Classifier: License :: OSI Approved :: GNU General Public License v3 (GPLv3)
Classifier: Natural Language :: English
Classifier: Operating System :: POSIX
Classifier: Topic :: Scientific/Engineering :: Astronomy
License-File: LICENSE
Requires-Dist: astropy>=3.2
Requires-Dist: numpy>=1.10
Requires-Dist: matplotlib>=2.0
Requires-Dist: scipy>=1.0
Requires-Dist: astLib>=0.12.0
Dynamic: author
Dynamic: author-email
